spherica/__init__.py
spherica/_main.py
spherica/main.py
spherica-0.4.4.dist-info/METADATA
spherica-0.4.4.dist-info/WHEEL
spherica-0.4.4.dist-info/top_level.txt
spherica-0.4.4.dist-info/RECORD
