Metadata-Version: 2.1
Name: spherica
Version: 0.4.4
Summary: S³ (kind of) in Python
Author: slycedf
License: MIT
Classifier: Development Status :: 3 - Alpha
